[
  {
    "cycle_id": 288,
    "asset": "ETH",
    "timeframe": "4h",
    "regime": "CHOP",
    "ts": "2026-03-10T06:32:07.897927+00:00"
  },
  {
    "cycle_id": 289,
    "asset": "BTC",
    "timeframe": "4h",
    "regime": "TRANSITION",
    "ts": "2026-03-10T06:37:08.395882+00:00"
  },
  {
    "cycle_id": 290,
    "asset": "SOL",
    "timeframe": "4h",
    "regime": "TRANSITION",
    "ts": "2026-03-10T06:42:08.800350+00:00"
  },
  {
    "cycle_id": 291,
    "asset": "TAO",
    "timeframe": "4h",
    "regime": "CHOP",
    "ts": "2026-03-10T06:47:08.419045+00:00"
  },
  {
    "cycle_id": 292,
    "asset": "DOGE",
    "timeframe": "4h",
    "regime": "CHOP",
    "ts": "2026-03-10T06:52:08.580090+00:00"
  },
  {
    "cycle_id": 293,
    "asset": "ETH",
    "timeframe": "1h",
    "regime": "TRANSITION",
    "ts": "2026-03-10T06:57:08.504947+00:00"
  },
  {
    "cycle_id": 293,
    "asset": "ETH",
    "timeframe": "4h",
    "regime": "CHOP",
    "ts": "2026-03-10T07:02:09.819283+00:00"
  },
  {
    "cycle_id": 293,
    "asset": "BTC",
    "timeframe": "4h",
    "regime": "TRANSITION",
    "ts": "2026-03-10T07:07:08.293799+00:00"
  },
  {
    "cycle_id": 294,
    "asset": "SOL",
    "timeframe": "4h",
    "regime": "TRANSITION",
    "ts": "2026-03-10T07:12:08.215230+00:00"
  },
  {
    "cycle_id": 295,
    "asset": "TAO",
    "timeframe": "4h",
    "regime": "CHOP",
    "ts": "2026-03-10T07:17:07.599174+00:00"
  },
  {
    "cycle_id": 296,
    "asset": "DOGE",
    "timeframe": "4h",
    "regime": "CHOP",
    "ts": "2026-03-10T07:22:08.475088+00:00"
  },
  {
    "cycle_id": 297,
    "asset": "ETH",
    "timeframe": "1h",
    "regime": "TRANSITION",
    "ts": "2026-03-10T07:27:11.653704+00:00"
  },
  {
    "cycle_id": 298,
    "asset": "ETH",
    "timeframe": "4h",
    "regime": "CHOP",
    "ts": "2026-03-10T07:32:07.418165+00:00"
  },
  {
    "cycle_id": 299,
    "asset": "BTC",
    "timeframe": "4h",
    "regime": "TRANSITION",
    "ts": "2026-03-10T07:37:08.010704+00:00"
  },
  {
    "cycle_id": 300,
    "asset": "SOL",
    "timeframe": "4h",
    "regime": "TRANSITION",
    "ts": "2026-03-10T07:42:08.205645+00:00"
  },
  {
    "cycle_id": 301,
    "asset": "TAO",
    "timeframe": "4h",
    "regime": "CHOP",
    "ts": "2026-03-10T07:47:08.221449+00:00"
  },
  {
    "cycle_id": 302,
    "asset": "DOGE",
    "timeframe": "4h",
    "regime": "CHOP",
    "ts": "2026-03-10T07:52:10.450106+00:00"
  },
  {
    "cycle_id": 303,
    "asset": "ETH",
    "timeframe": "1h",
    "regime": "TRANSITION",
    "ts": "2026-03-10T08:02:07.575118+00:00"
  },
  {
    "cycle_id": 304,
    "asset": "ETH",
    "timeframe": "4h",
    "regime": "CHOP",
    "ts": "2026-03-10T08:07:08.214456+00:00"
  },
  {
    "cycle_id": 305,
    "asset": "BTC",
    "timeframe": "4h",
    "regime": "TRANSITION",
    "ts": "2026-03-10T08:12:08.990704+00:00"
  }
]